rx/__init__.py
rx/multi.py
rx/stats.py
tests/__init__.py
tests/multi_tests.py
synthetic_rx-0.1.5.dist-info/METADATA
synthetic_rx-0.1.5.dist-info/WHEEL
synthetic_rx-0.1.5.dist-info/top_level.txt
synthetic_rx-0.1.5.dist-info/RECORD
