Metadata-Version: 2.1
Name: synthetic-rx
Version: 0.1.5
Summary: Synthetic Rx Generator Library
Home-page: UNKNOWN
Author: Aaryan Agarwal, Shirish Singh
Author-email: aaryanagarwalinus@gmail.com
License: MIT
Platform: UNKNOWN
Classifier: Intended Audience :: Developers
Classifier: License :: OSI Approved :: MIT License
Classifier: Programming Language :: Python
Classifier: Programming Language :: Python :: 3
Classifier: Programming Language :: Python :: 3.6
Classifier: Programming Language :: Python :: 3.7
Classifier: Programming Language :: Python :: 3.8
Classifier: Programming Language :: Python :: 3.9
Classifier: Operating System :: OS Independent
Requires-Dist: numpy
Requires-Dist: pandas
Requires-Dist: scipy
Requires-Dist: scikit-learn
Requires-Dist: reportlab
Requires-Dist: matplotlib
